<?xml version="1.0" encoding="utf-8"?>
	<annotation>
		<folder>driving_annotation_dataset</folder>
		<filename>1360.jpg</filename>
		<size>
			<width>1148</width>
			<height>648</height>
			<depth>3</depth>
		</size>
		<object>
			<name>adult</name>
			<pose>Unspecified</pose>
			<truncated>0</truncated>
			<difficult>0</difficult>
			<bndbox>
				<xmin>410</xmin>
				<ymin>336</ymin>
				<xmax>541</xmax>
				<ymax>538</ymax>
			</bndbox>
		</object>
		<object>
			<name>adult</name>
			<pose>Unspecified</pose>
			<truncated>0</truncated>
			<difficult>0</difficult>
			<bndbox>
				<xmin>220</xmin>
				<ymin>93</ymin>
				<xmax>295</xmax>
				<ymax>270</ymax>
			</bndbox>
		</object>
		<object>
			<name>adult</name>
			<pose>Unspecified</pose>
			<truncated>0</truncated>
			<difficult>0</difficult>
			<bndbox>
				<xmin>893</xmin>
				<ymin>568</ymin>
				<xmax>995</xmax>
				<ymax>649</ymax>
			</bndbox>
		</object>
		<object>
			<name>child</name>
			<pose>Unspecified</pose>
			<truncated>0</truncated>
			<difficult>0</difficult>
			<bndbox>
				<xmin>224</xmin>
				<ymin>296</ymin>
				<xmax>290</xmax>
				<ymax>455</ymax>
			</bndbox>
		</object>
		<object>
			<name>child</name>
			<pose>Unspecified</pose>
			<truncated>0</truncated>
			<difficult>0</difficult>
			<bndbox>
				<xmin>285</xmin>
				<ymin>449</ymin>
				<xmax>381</xmax>
				<ymax>598</ymax>
			</bndbox>
		</object>
		<object>
			<name>child</name>
			<pose>Unspecified</pose>
			<truncated>0</truncated>
			<difficult>0</difficult>
			<bndbox>
				<xmin>682</xmin>
				<ymin>374</ymin>
				<xmax>810</xmax>
				<ymax>617</ymax>
			</bndbox>
		</object>
		<object>
			<name>child</name>
			<pose>Unspecified</pose>
			<truncated>0</truncated>
			<difficult>0</difficult>
			<bndbox>
				<xmin>810</xmin>
				<ymin>323</ymin>
				<xmax>878</xmax>
				<ymax>551</ymax>
			</bndbox>
		</object>
		<object>
			<name>child</name>
			<pose>Unspecified</pose>
			<truncated>0</truncated>
			<difficult>0</difficult>
			<bndbox>
				<xmin>905</xmin>
				<ymin>318</ymin>
				<xmax>970</xmax>
				<ymax>513</ymax>
			</bndbox>
		</object>
		<object>
			<name>child</name>
			<pose>Unspecified</pose>
			<truncated>0</truncated>
			<difficult>0</difficult>
			<bndbox>
				<xmin>988</xmin>
				<ymin>532</ymin>
				<xmax>1076</xmax>
				<ymax>647</ymax>
			</bndbox>
		</object>
	</annotation>
