<annotation>
	<folder>sing03</folder>
	<filename>Adult&amp;Child339.jpg</filename>
	<path>C:\Users\q5980\Videos\报警\sing03\Adult&amp;Child339.jpg</path>
	<source>
		<database>Unknown</database>
	</source>
	<size>
		<width>245</width>
		<height>157</height>
		<depth>3</depth>
	</size>
	<segmented>0</segmented>
	<object>
		<name>adult</name>
		<pose>Unspecified</pose>
		<truncated>0</truncated>
		<difficult>0</difficult>
		<bndbox>
			<xmin>14</xmin>
			<ymin>26</ymin>
			<xmax>50</xmax>
			<ymax>71</ymax>
		</bndbox>
	</object>
	<object>
		<name>child</name>
		<pose>Unspecified</pose>
		<truncated>0</truncated>
		<difficult>0</difficult>
		<bndbox>
			<xmin>91</xmin>
			<ymin>36</ymin>
			<xmax>117</xmax>
			<ymax>66</ymax>
		</bndbox>
	</object>
	<object>
		<name>child</name>
		<pose>Unspecified</pose>
		<truncated>0</truncated>
		<difficult>0</difficult>
		<bndbox>
			<xmin>127</xmin>
			<ymin>29</ymin>
			<xmax>148</xmax>
			<ymax>58</ymax>
		</bndbox>
	</object>
	<object>
		<name>child</name>
		<pose>Unspecified</pose>
		<truncated>0</truncated>
		<difficult>0</difficult>
		<bndbox>
			<xmin>110</xmin>
			<ymin>23</ymin>
			<xmax>123</xmax>
			<ymax>45</ymax>
		</bndbox>
	</object>
</annotation>
