<annotation>
	<folder>sing03</folder>
	<filename>Adult&amp;Child245.jpg</filename>
	<path>C:\Users\q5980\Videos\报警\sing03\Adult&amp;Child245.jpg</path>
	<source>
		<database>Unknown</database>
	</source>
	<size>
		<width>270</width>
		<height>164</height>
		<depth>3</depth>
	</size>
	<segmented>0</segmented>
	<object>
		<name>adult</name>
		<pose>Unspecified</pose>
		<truncated>0</truncated>
		<difficult>0</difficult>
		<bndbox>
			<xmin>229</xmin>
			<ymin>42</ymin>
			<xmax>252</xmax>
			<ymax>72</ymax>
		</bndbox>
	</object>
	<object>
		<name>adult</name>
		<pose>Unspecified</pose>
		<truncated>0</truncated>
		<difficult>0</difficult>
		<bndbox>
			<xmin>226</xmin>
			<ymin>25</ymin>
			<xmax>249</xmax>
			<ymax>40</ymax>
		</bndbox>
	</object>
	<object>
		<name>adult</name>
		<pose>Unspecified</pose>
		<truncated>0</truncated>
		<difficult>0</difficult>
		<bndbox>
			<xmin>43</xmin>
			<ymin>12</ymin>
			<xmax>79</xmax>
			<ymax>41</ymax>
		</bndbox>
	</object>
</annotation>
