<annotation>
	<folder>baidu02</folder>
	<filename>幼儿园	(64).jpg</filename>
	<path>D:\BaiduNetdiskDownload\图片\baidu02\幼儿园	(64).jpg</path>
	<source>
		<database>Unknown</database>
	</source>
	<size>
		<width>800</width>
		<height>800</height>
		<depth>3</depth>
	</size>
	<segmented>0</segmented>
	<object>
		<name>adult</name>
		<pose>Unspecified</pose>
		<truncated>0</truncated>
		<difficult>0</difficult>
		<bndbox>
			<xmin>89</xmin>
			<ymin>7</ymin>
			<xmax>677</xmax>
			<ymax>799</ymax>
		</bndbox>
	</object>
</annotation>
